spectrumm/__init__.py
spectrumm/cli.py
spectrumm-0.1.2.dist-info/entry_points.txt
spectrumm-0.1.2.dist-info/WHEEL
spectrumm-0.1.2.dist-info/METADATA
spectrumm-0.1.2.dist-info/RECORD
